stidapi/__init__.py
stidapi/doc.py
stidapi/plant.py
stidapi/system.py
stidapi/tag.py
stidapi/utils.py
stidapi-1.3.4.dist-info/METADATA
stidapi-1.3.4.dist-info/WHEEL
stidapi-1.3.4.dist-info/RECORD
