Metadata-Version: 2.1
Name: stidapi
Version: 1.3.4
Summary: Python client for connecting to Equinor STIDapi
License: Proprietary
Author: Åsmund Våge Fannemel
Author-email: asmf@equinor.com
Requires-Python: >=3.9.2,<4.0.0
Classifier: License :: Other/Proprietary License
Classifier: Programming Language :: Python :: 3
Classifier: Programming Language :: Python :: 3.10
Classifier: Programming Language :: Python :: 3.11
Classifier: Programming Language :: Python :: 3.12
Classifier: Programming Language :: Python :: 3.13
Requires-Dist: certifi (>=2024.11.17)
Requires-Dist: msal-bearer (>=1.3.0,<2.0.0)
Requires-Dist: requests (>=2.31.0,<3.0.0)
Project-URL: repository, https://github.com/equinor/STIDapi-python
